pioneer/common/IoU3d.py
pioneer/common/banks.py
pioneer/common/calibration.py
pioneer/common/chessboard.py
pioneer/common/clouds.py
pioneer/common/colors.py
pioneer/common/constants.py
pioneer/common/cylindrical_projection.py
pioneer/common/icp_method.py
pioneer/common/images.py
pioneer/common/imu_utils.py
pioneer/common/interpolator.py
pioneer/common/linalg.py
pioneer/common/logging_manager.py
pioneer/common/mercator_projection.py
pioneer/common/misc.py
pioneer/common/peak_detector.py
pioneer/common/plane.py
pioneer/common/platform.py
pioneer/common/times.py
pioneer/common/trace_processing.py
pioneer/common/video.py
pioneer/common/zip.py
pioneer/common/types/__init__.py
pioneer/common/types/calibration.py
pioneer/common/types/option.py
pioneer/common/types/result.py
pioneer_common-1.3.1.dist-info/DESCRIPTION.rst
pioneer_common-1.3.1.dist-info/METADATA
pioneer_common-1.3.1.dist-info/RECORD
pioneer_common-1.3.1.dist-info/WHEEL
pioneer_common-1.3.1.dist-info/metadata.json
pioneer_common-1.3.1.dist-info/top_level.txt
