Metadata-Version: 2.0
Name: pioneer-common
Version: 1.3.1
Summary: Pioneer team common utilities
Home-page: UNKNOWN
Author: Leddartech
License: UNKNOWN
Platform: UNKNOWN
Classifier: Programming Language :: Python :: 3
Classifier: License :: OSI Approved :: MIT License
Classifier: Operating System :: OS Independent
Requires-Python: >=3.6
Requires-Dist: future
Requires-Dist: matplotlib
Requires-Dist: numpy
Requires-Dist: open3d
Requires-Dist: opencv-python
Requires-Dist: pyquaternion
Requires-Dist: ruamel.std.zipfile
Requires-Dist: scikit-build
Requires-Dist: scipy
Requires-Dist: shapely
Requires-Dist: sk-video
Requires-Dist: sklearn
Requires-Dist: tqdm
Requires-Dist: transforms3d
Requires-Dist: utm
